asyncreq/__init__.py
asyncreq/network.py
asyncreq-0.0.6.dist-info/METADATA
asyncreq-0.0.6.dist-info/WHEEL
asyncreq-0.0.6.dist-info/licenses/LICENSE.md
asyncreq-0.0.6.dist-info/RECORD
