Metadata-Version: 2.1
Name: asyncreq
Version: 0.0.6
Summary: A lightweight library for making asynchronous HTTP requests.
Project-URL: Homepage, https://git.slc.ar/slococo/asyncreq
Project-URL: Repository, https://git.slc.ar/slococo/asyncreq
Author-email: Santiago Lo Coco <mail@slococo.com.ar>
License-Expression: MIT
License-File: LICENSE.md
Classifier: Intended Audience :: Developers
Classifier: Intended Audience :: Information Technology
Classifier: Intended Audience :: System Administrators
Classifier: License :: OSI Approved :: MIT License
Classifier: Operating System :: OS Independent
Classifier: Programming Language :: Python
Classifier: Programming Language :: Python :: 3
Classifier: Programming Language :: Python :: 3 :: Only
Classifier: Programming Language :: Python :: 3.8
Classifier: Programming Language :: Python :: 3.9
Classifier: Programming Language :: Python :: 3.10
Classifier: Programming Language :: Python :: 3.11
Classifier: Topic :: Internet
Classifier: Topic :: Software Development
Classifier: Topic :: Software Development :: Libraries
Classifier: Topic :: Software Development :: Libraries :: Python Modules
Classifier: Typing :: Typed
Requires-Python: >=3.8
Requires-Dist: aiohttp>=3.8.6
Requires-Dist: async-timeout>=4.0.3
Requires-Dist: fastapi>=0.103.2
